ewha_parking_dynamicP/__init__.py
ewha_parking_dynamicP/frequent_parking.py
ewha_parking_dynamicP/illegal_parking.py
ewha_parking_dynamicp-0.1.1.dist-info/METADATA
ewha_parking_dynamicp-0.1.1.dist-info/WHEEL
ewha_parking_dynamicp-0.1.1.dist-info/top_level.txt
ewha_parking_dynamicp-0.1.1.dist-info/RECORD
