Metadata-Version: 2.4
Name: ewha_parking_dynamicP
Version: 0.1.1
Summary: Analyze frequent and illegal parking patterns using trajectory and GIS data
Author-email: Jiwon Kim <kimjiwon4007@ewha.ac.kr>
Requires-Python: >=3.9
Requires-Dist: pandas>=2.0
Requires-Dist: numpy>=1.24
Requires-Dist: geopandas>=0.14
Requires-Dist: shapely>=2.0
